async_rwlock/__init__.py
async_rwlock-0.1.0.dist-info/METADATA
async_rwlock-0.1.0.dist-info/WHEEL
async_rwlock-0.1.0.dist-info/licenses/LICENSE
async_rwlock-0.1.0.dist-info/RECORD
